tree_sitter_starlark/__init__.py
tree_sitter_starlark/_binding.abi3.so
tree_sitter_starlark/binding.c
tree_sitter_starlark/__init__.pyi
tree_sitter_starlark/py.typed
tree_sitter_starlark/queries/folds.scm
tree_sitter_starlark/queries/highlights.scm
tree_sitter_starlark/queries/indents.scm
tree_sitter_starlark/queries/injections.scm
tree_sitter_starlark/queries/locals.scm
tree_sitter_starlark-1.3.0.dist-info/top_level.txt
tree_sitter_starlark-1.3.0.dist-info/RECORD
tree_sitter_starlark-1.3.0.dist-info/LICENSE
tree_sitter_starlark-1.3.0.dist-info/METADATA
tree_sitter_starlark-1.3.0.dist-info/WHEEL
